{
  "project_info": {
    "project_number": "938102908733",
    "project_id": "yonomi-flutter-demo-staging",
    "storage_bucket": "yonomi-flutter-demo-staging.appspot.com"
  },
  "client": [
    {
      "client_info": {
        "mobilesdk_app_id": "1:938102908733:android:d1fe15bdc6aa9d5ec10754",
        "android_client_info": {
          "package_name": "co.yonomi.flutter_demo"
        }
      },
      "oauth_client": [
        {
          "client_id": "938102908733-29n2pu55t3suvb98dl371h43rrki4llk.apps.googleusercontent.com",
          "client_type": 3
        }
      ],
      "api_key": [
        {
          "current_key": "AIzaSyAAPt5kBEi6p8hYa2BMB72ynSbC0IlFeJU"
        }
      ],
      "services": {
        "appinvite_service": {
          "other_platform_oauth_client": [
            {
              "client_id": "938102908733-29n2pu55t3suvb98dl371h43rrki4llk.apps.googleusercontent.com",
              "client_type": 3
            },
            {
              "client_id": "938102908733-ihtd7u0aqo3qpj0mln0nst6595jk7euc.apps.googleusercontent.com",
              "client_type": 2,
              "ios_info": {
                "bundle_id": "com.yonomi.flutterDemo"
              }
            }
          ]
        }
      }
    }
  ],
  "configuration_version": "1"
}